debpacker/__init__.py
debpacker/__main__.py
debpacker-2.1.4.dist-info/LICENSE
debpacker-2.1.4.dist-info/METADATA
debpacker-2.1.4.dist-info/WHEEL
debpacker-2.1.4.dist-info/entry_points.txt
debpacker-2.1.4.dist-info/top_level.txt
debpacker-2.1.4.dist-info/RECORD
