Metadata-Version: 2.1
Name: debpacker
Version: 2.1.4
Summary: A tool to help pack projects as a DEB file
Home-page: https://github.com/zmarffy/debpacker
Author: Zeke Marffy
Author-email: zmarffy@yahoo.com
License: MIT
Platform: UNKNOWN
Requires-Python: >=3.6
Requires-Dist: pytz
Requires-Dist: tzlocal
Requires-Dist: zmtools
